[
	{ "minValue": 47,     "maxValue": 48,     "swosValue": "25K", 	"desiredSum":1  },
	{ "minValue": 48,     "maxValue": 49,     "swosValue": "30K", 	"desiredSum":2  },
	{ "minValue": 49,     "maxValue": 50,     "swosValue": "40K", 	"desiredSum":3  },
	{ "minValue": 50,     "maxValue": 51,     "swosValue": "50K", 	"desiredSum":4  },
	{ "minValue": 51,     "maxValue": 52,    "swosValue": "65K", 	"desiredSum":5  },
	{ "minValue": 52,    "maxValue": 53,    "swosValue": "75K", 	"desiredSum":6  },
	{ "minValue": 53,    "maxValue": 54,    "swosValue": "85K", 	"desiredSum":7  },
	{ "minValue": 54,    "maxValue": 55,    "swosValue": "100K", 	"desiredSum":8 },
	{ "minValue": 55,    "maxValue": 56,    "swosValue": "110K", 	"desiredSum":9 },
	{ "minValue": 56,    "maxValue": 57,    "swosValue": "130K", 	"desiredSum":10 },
	{ "minValue": 57,    "maxValue": 58,    "swosValue": "150K", 	"desiredSum":11 },
	{ "minValue": 58,    "maxValue": 59,    "swosValue": "160K", 	"desiredSum":12 },
	{ "minValue": 59,    "maxValue": 60,    "swosValue": "180K", 	"desiredSum":13 },
	{ "minValue": 60,    "maxValue": 61,    "swosValue": "200K", 	"desiredSum":14 },
	{ "minValue": 61,    "maxValue": 62,    "swosValue": "250K", 	"desiredSum":15 },
	{ "minValue": 62,    "maxValue": 63,    "swosValue": "300K", 	"desiredSum":16 },
	{ "minValue": 63,    "maxValue": 64,   "swosValue": "350K", 	"desiredSum":17 },
	{ "minValue": 64,   "maxValue": 65,   "swosValue": "450K", 	"desiredSum":18 },
	{ "minValue": 65,   "maxValue": 66,   "swosValue": "500K", 	"desiredSum":19 },
	{ "minValue": 66,   "maxValue": 67,   "swosValue": "550K", 	"desiredSum":20 },
	{ "minValue": 67,   "maxValue": 68,   "swosValue": "600K", 	"desiredSum":21 },
	{ "minValue": 68,   "maxValue": 69,   "swosValue": "650K", 	"desiredSum":22 },
	{ "minValue": 69,   "maxValue": 70,   "swosValue": "700K", 	"desiredSum":23 },
	{ "minValue": 70,   "maxValue": 71,   "swosValue": "750K", 	"desiredSum":24 },
	{ "minValue": 71,   "maxValue": 72,   "swosValue": "800K", 	"desiredSum":25 },
	{ "minValue": 72,   "maxValue": 73,   "swosValue": "850K", 	"desiredSum":26 },
	{ "minValue": 73,   "maxValue": 74,   "swosValue": "950K", 	"desiredSum":27 },
	{ "minValue": 74,   "maxValue": 75,   "swosValue": "1M", 		"desiredSum":28   },
	{ "minValue": 75,   "maxValue": 76,   "swosValue": "1.1M", 	"desiredSum":29 },
	{ "minValue": 76,   "maxValue": 77,   "swosValue": "1.3M", 	"desiredSum":30 },
	{ "minValue": 77,   "maxValue": 78,   "swosValue": "1.5M", 	"desiredSum":31 },
	{ "minValue": 78,   "maxValue": 79,   "swosValue": "1.6M", 	"desiredSum":32 },
	{ "minValue": 79,   "maxValue": 80,   "swosValue": "1.8M", 	"desiredSum":33 },
	{ "minValue": 80,   "maxValue": 81,  "swosValue": "1.9M", 	"desiredSum":34 },
	{ "minValue": 81,  "maxValue": 82,  "swosValue": "2M", 		"desiredSum":35   },
	{ "minValue": 82,  "maxValue": 83,  "swosValue": "2.25M", 	"desiredSum":36},
	{ "minValue": 83,  "maxValue": 84,  "swosValue": "2.75M", 	"desiredSum":37},
	{ "minValue": 84,  "maxValue": 85,  "swosValue": "3M", 		"desiredSum":38   },
	{ "minValue": 85,  "maxValue": 86,  "swosValue": "3.5M", 	"desiredSum":39 },
	{ "minValue": 86,  "maxValue": 87,  "swosValue": "4.5M", 	"desiredSum":40 },
	{ "minValue": 87,  "maxValue": 88,  "swosValue": "5M", 		"desiredSum":41   },
	{ "minValue": 88,  "maxValue": 89,  "swosValue": "6M", 		"desiredSum":42   },
	{ "minValue": 89,  "maxValue": 90,  "swosValue": "7M", 		"desiredSum":43   },
	{ "minValue": 90,  "maxValue": 91,  "swosValue": "8M",		"desiredSum":44   },
	{ "minValue": 91,  "maxValue": 92,  "swosValue": "9M", 		"desiredSum":45   },
	{ "minValue": 92,  "maxValue": 93, "swosValue": "10M", 	"desiredSum":46  },
	{ "minValue": 93, "maxValue": 94, "swosValue": "12M", 	"desiredSum":47  },
	{ "minValue": 94, "maxValue": 99, "swosValue": "15M", 	"desiredSum":48 }
]
